czipdecrypter.cpython-36m-x86_64-linux-gnu.so
cZipDecrypter-0.0.1.dist-info/RECORD
cZipDecrypter-0.0.1.dist-info/METADATA
cZipDecrypter-0.0.1.dist-info/top_level.txt
cZipDecrypter-0.0.1.dist-info/WHEEL
cZipDecrypter-0.0.1.dist-info/LICENSE
