Metadata-Version: 2.1
Name: cZipDecrypter
Version: 0.0.1
Summary: Drip-in replacement of zipfile._ZipDecrypter for python 3.7+
Home-page: https://github.com/multiSnow/czipdecrypter
Author: multiSnow
Author-email: infinity.blick.winkel@gmail.com
License: UNKNOWN
Keywords: zipfile,zip,decryption
Platform: UNKNOWN
Classifier: Development Status :: 3 - Alpha
Classifier: License :: OSI Approved :: ISC License (ISCL)
Classifier: Programming Language :: C
Classifier: Programming Language :: Cython
